charcount/__init__.py
charcount/char_count.py
char_count_example_pkg_asomchik_NEW-0.0.4.dist-info/LICENSE
char_count_example_pkg_asomchik_NEW-0.0.4.dist-info/METADATA
char_count_example_pkg_asomchik_NEW-0.0.4.dist-info/WHEEL
char_count_example_pkg_asomchik_NEW-0.0.4.dist-info/top_level.txt
char_count_example_pkg_asomchik_NEW-0.0.4.dist-info/RECORD
